Metadata-Version: 1.1
Name: LEGODEV
Version: 0.0.2
Summary: Libraries to assist competitors with common tasks or sequence of tasks
Home-page: UNKNOWN
Author: Muhammed Hamzah, Thabeeshan Sarathasegaram, Vinu Venkatesh Muthukumar, Jiafei Lin
Author-email: wropythonmodule@gmail.com
License: MIT
Keywords: legodev
Platform: UNKNOWN
Classifier: Development Status :: 5 - Production/Stable
Classifier: Intended Audience :: Education
Classifier: Operating System :: Microsoft :: Windows :: Windows 10
Classifier: License :: OSI Approved :: MIT License
Classifier: Programming Language :: Python :: 3
